sinapsis_huggingface_hub/__init__.py
sinapsis_huggingface_hub/helpers/__init__.py
sinapsis_huggingface_hub/helpers/tags.py
sinapsis_huggingface_hub/templates/__init__.py
sinapsis_huggingface_hub/templates/huggingface_downloader.py
sinapsis_huggingface_hub-0.1.0.dist-info/licenses/LICENSE
sinapsis_huggingface_hub-0.1.0.dist-info/METADATA
sinapsis_huggingface_hub-0.1.0.dist-info/WHEEL
sinapsis_huggingface_hub-0.1.0.dist-info/top_level.txt
sinapsis_huggingface_hub-0.1.0.dist-info/RECORD
