Metadata-Version: 2.4
Name: sinapsis-huggingface-hub
Version: 0.1.0
Summary: Templates for managing Hugging Face models, spaces and datasets.
Author-email: SinapsisAI <dev@sinapsis.tech>
Project-URL: Homepage, https://sinapsis.tech
Project-URL: Documentation, https://docs.sinapsis.tech/docs
Project-URL: Tutorials, https://docs.sinapsis.tech/tutorials
Project-URL: Repository, https://github.com/Sinapsis-AI/sinapsis-huggingface.git
Requires-Python: >=3.10
License-File: LICENSE
Requires-Dist: huggingface-hub>=0.34.4
Requires-Dist: sinapsis>=0.2.22
Provides-Extra: hf-xet
Requires-Dist: huggingface-hub[hf-xet]>=0.34.4; extra == "hf-xet"
Provides-Extra: all
Requires-Dist: sinapsis-huggingface-hub[hf-xet]; extra == "all"
Dynamic: license-file
